publish_test/__init__.py
publish_test-0.1.0.dist-info/WHEEL
publish_test-0.1.0.dist-info/METADATA
publish_test-0.1.0.dist-info/RECORD
